burocrata/__init__.py
burocrata/_version.py
burocrata/cli.py
burocrata-0.3.0.dist-info/licenses/AUTHORS.md
burocrata-0.3.0.dist-info/licenses/LICENSE.txt
burocrata-0.3.0.dist-info/METADATA
burocrata-0.3.0.dist-info/WHEEL
burocrata-0.3.0.dist-info/entry_points.txt
burocrata-0.3.0.dist-info/top_level.txt
burocrata-0.3.0.dist-info/RECORD
