Metadata-Version: 2.4
Name: burocrata
Version: 0.3.0
Summary: Check and insert copyright and license notices into source code
Author-email: The Burocrata Developers <fatiandoaterra@protonmail.com>
Maintainer-email: Leonardo Uieda <leo@uieda.com>
License-Expression: MIT
Project-URL: Homepage, https://github.com/fatiando/burocrata
Project-URL: Changelog, https://github.com/fatiando/burocrata/blob/main/CHANGELOG.md
Project-URL: Bug Tracker, https://github.com/fatiando/burocrata/issues
Project-URL: Source Code, https://github.com/fatiando/burocrata
Keywords: license,development,copyright
Classifier: Development Status :: 4 - Beta
Classifier: Operating System :: OS Independent
Classifier: Intended Audience :: Developers
Classifier: Topic :: Software Development :: Libraries
Classifier: Programming Language :: Python :: 3
Classifier: Programming Language :: Python :: 3.9
Classifier: Programming Language :: Python :: 3.10
Classifier: Programming Language :: Python :: 3.11
Classifier: Programming Language :: Python :: 3.12
Classifier: Programming Language :: Python :: 3.13
Requires-Python: >=3.9
License-File: LICENSE.txt
License-File: AUTHORS.md
Requires-Dist: click<9.0.0,>=8.0.0
Requires-Dist: tomli<3.0.0,>=1.1.0
Requires-Dist: pathspec>=0.10.1
Dynamic: license-file
